kafkars/__init__.py
kafkars/_lib.cpython-313t-x86_64-linux-gnu.so
kafkars/schema.py
kafkars/source_topic.py
kafkars-0.0.4.dist-info/METADATA
kafkars-0.0.4.dist-info/WHEEL
kafkars-0.0.4.dist-info/licenses/LICENSE
kafkars-0.0.4.dist-info/RECORD
