Metadata-Version: 2.4
Name: kafkars
Version: 0.0.4
Classifier: Programming Language :: Python :: 3 :: Only
Classifier: Programming Language :: Python :: 3.10
Classifier: Programming Language :: Python :: 3.11
Classifier: Programming Language :: Python :: 3.12
Classifier: Programming Language :: Python :: 3.13
Classifier: Programming Language :: Python :: 3.14
Requires-Dist: pyarrow>=14
Requires-Dist: mkdocs-material>=9 ; extra == 'docs'
Requires-Dist: mkdocs-mermaid2-plugin>=1 ; extra == 'docs'
Requires-Dist: mkdocstrings[python]>=0.24 ; extra == 'docs'
Provides-Extra: docs
License-File: LICENSE
Summary: Rust based, Arrow powered, python kafka client
License: Apache-2.0
Requires-Python: >=3.10
